geodistance/Geodistance.py
geodistance/__init__.py
geodistance-0.2.0.dist-info/METADATA
geodistance-0.2.0.dist-info/WHEEL
geodistance-0.2.0.dist-info/top_level.txt
geodistance-0.2.0.dist-info/RECORD
