Metadata-Version: 2.1
Name: geodistance
Version: 0.2.0
Summary: Distance calculation library
Home-page: https://geodistance.readthedocs.io/
Author: Adebayo Adeoye
Author-email: adeoyeadebayo18@gmail.com
License: MIT
Platform: UNKNOWN
Classifier: Intended Audience :: Developers
Classifier: License :: OSI Approved :: MIT License
Classifier: Programming Language :: Python
Classifier: Programming Language :: Python :: 3
Classifier: Programming Language :: Python :: 3.6
Classifier: Programming Language :: Python :: 3.7
Classifier: Programming Language :: Python :: 3.8
Classifier: Programming Language :: Python :: 3.9
Classifier: Operating System :: OS Independent
